netweaver/__init__.py
netweaver/_internal_utils.py
netweaver/accuracy.py
netweaver/activation_layers.py
netweaver/datasets.py
netweaver/layers.py
netweaver/lossfunctions.py
netweaver/model.py
netweaver/optimizers.py
netweaver/softmax_cce_loss.py
netweaver/utils.py
netweaver-1.0.2.dist-info/METADATA
netweaver-1.0.2.dist-info/WHEEL
netweaver-1.0.2.dist-info/licenses/LICENSE.txt
netweaver-1.0.2.dist-info/RECORD
