Metadata-Version: 2.4
Name: netweaver
Version: 1.0.2
Summary: Neural Network from Scratch
Project-URL: Homepage, https://github.com/vabsalack/Netweaver
Project-URL: Repository, https://github.com/vabsalack/Netweaver
Project-URL: Issues, https://github.com/vabsalack/Netweaver
Author-email: keerthivasan <keerthi.pydev@gmail.com>
Maintainer-email: keerthivasan <keerthi.pydev@gmail.com>
License-Expression: MIT
License-File: LICENSE.txt
Keywords: ai,artificial intelligence,deep learning,machine learning,neural network,numpy,python
Classifier: Development Status :: 5 - Production/Stable
Classifier: Intended Audience :: Developers
Classifier: Intended Audience :: Education
Classifier: License :: OSI Approved :: MIT License
Classifier: Natural Language :: English
Classifier: Operating System :: OS Independent
Classifier: Programming Language :: Python :: 3.10
Classifier: Programming Language :: Python :: 3.11
Classifier: Programming Language :: Python :: 3.12
Classifier: Programming Language :: Python :: 3.13
Classifier: Programming Language :: Python :: Implementation :: CPython
Classifier: Topic :: Education
Classifier: Topic :: Scientific/Engineering :: Artificial Intelligence
Classifier: Topic :: Software Development :: Libraries :: Python Modules
Requires-Python: >=3.11
Requires-Dist: ipympl>=0.9.7
Requires-Dist: jupyter>=1.1.1
Requires-Dist: matplotlib>=3.10.1
Requires-Dist: numpy>=2.2.4
Requires-Dist: pandas>=2.2.3
Requires-Dist: pympler>=1.1
Requires-Dist: tqdm>=4.67.1
